{
  "name": "PP",
  "default_attributes": {
    "authorization": {
      "ad_auth": {
        "ad_network": "BETADMZ"
      },
     "sudo": {
       "groups": [
         "domain-admins",
         "BETADMZ\\\\domain-admins"
       ],
       "users": [
        "shaggy"
       ],
       "passwordless": false
     }
    },      
    "vc2010x86": {
      "url": "http://repo.netiq.dmz/repo/windows/ms_vc2010/vcredist_x86.exe"
    },
    "vc2010x64": {
      "url": "http://repo.netiq.dmz/repo/windows/ms_vc2010/vcredist_x64.exe"
    },
    "wt_dx": {
      "app_settings_section": {
        "streamingServiceRoot": "https://ppws.webtrends.com/StreamingServices_v3/"
      },
      "cacheenabled": "True",
      "brandedaccountid": "20578,20663",
      "cachename": "DX",
      "website_name": "DX",
      "website_port": "80",
      "endpoint_address": "net.tcp://<REPLACE>:8096/SearchService/Search"
    },
    "wt_common": {
      "install_dir": "d:\\wrs",
      "cassandra_report_column": "01_Report",
      "installlog_dir": "d:\\logs",
      "cassandra_snmp_comm": "wtlive",
      "cassandra_hosts": [
        "cas.beta.dmz"
      ],
      "wrsread_group": "<REPLACE>",
      "cassandra_snmp_port": "1161",
      "schedulerdb_host": "<lasppmaster01.beta.dmz",
      "sched_host": "lasppmaster01.beta.dmz",
      "cache_hosts": [
        {
          "name": "lasppcache01v.beta.dmz",
          "port": "11211"
        },
        {
          "name": "lasppcache01v.beta.dmz",
          "port": "11211"
        },
	{
          "name": "lasppcache01v.beta.dmz",
          "port": "11211"
        }
      ],
      "cassandra_meta_column": "01_Meta",
      "velocitycache_hosts": [
        {
          "name": "lasvcache01v.beta.dmz",
          "port": "22233"
        },
        {
          "name": "lasvcache02v.beta.dmz",
          "port": "22233"
        },
	{
          "name": "lasvcache03v.beta.dmz",
          "port": "22233"
        }
      ],
      "wrsmodify_group": "<REPLACE>",
      "master_host": "lasppmaster01.beta.dmz",
      "cassandra_thrift_port": "9160",
      "usage_host": "lasppmaster01.beta.dmz",
      "rta_host": "laspprta01v.beta.dmz"
    },
    "memcached": {
      "memory": "2048"
    },
    "ntp": {
      "servers": [
        "ntp.pdx.netiq.dmz",
	"ntp.las.netiq.dmz",
	"ntp.iad.netiq.dmz",
	"ntp.ams.netiq.dmz"
      ]
    },
    "java": {
      "install_flavor": "oracle",
      "jdk_version": "6"
    }
  },
  "json_class": "Chef::Environment",
  "description": "PP Pod",
  "cookbook_versions": {
  },
  "override_attributes": {
  },
  "chef_type": "environment"
}
